asyncgui_ext/clock.py
asyncgui_ext_clock-0.6.1.dist-info/LICENSE
asyncgui_ext_clock-0.6.1.dist-info/METADATA
asyncgui_ext_clock-0.6.1.dist-info/WHEEL
asyncgui_ext_clock-0.6.1.dist-info/RECORD
