Metadata-Version: 2.3
Name: asyncgui-ext-clock
Version: 0.6.1
Summary: An event scheduler for asyncgui programs
License: MIT
Keywords: async
Author: Nattōsai Mitō
Author-email: flow4re2c@gmail.com
Requires-Python: >=3.10,<4.0
Classifier: Development Status :: 2 - Pre-Alpha
Classifier: Intended Audience :: Developers
Classifier: License :: OSI Approved :: MIT License
Classifier: Operating System :: OS Independent
Classifier: Programming Language :: Python
Classifier: Programming Language :: Python :: 3
Classifier: Programming Language :: Python :: 3.10
Classifier: Programming Language :: Python :: 3.11
Classifier: Programming Language :: Python :: 3.12
Classifier: Programming Language :: Python :: 3.13
Classifier: Topic :: Software Development :: Libraries
Requires-Dist: asyncgui (>=0.9.3,<0.10)
Project-URL: Homepage, https://github.com/asyncgui/asyncgui-ext-clock
Project-URL: Repository, https://github.com/asyncgui/asyncgui-ext-clock
